pytorch2keras/__init__.py
pytorch2keras/converter.py
pytorch2keras/layers.py
pytorch2keras-0.1.5.dist-info/METADATA
pytorch2keras-0.1.5.dist-info/RECORD
pytorch2keras-0.1.5.dist-info/WHEEL
pytorch2keras-0.1.5.dist-info/top_level.txt
tests/__init__.py
tests/alexnet.py
tests/avg_pool.py
tests/bn.py
tests/concat_many.py
tests/const.py
tests/conv2d.py
tests/conv2d_channels_last.py
tests/conv2d_dilation.py
tests/conv3d.py
tests/convtranspose2d.py
tests/dense.py
tests/densenet.py
tests/droupout.py
tests/embedding.py
tests/lrelu.py
tests/max_pool.py
tests/max_pool3d.py
tests/mul.py
tests/multiple_inputs.py
tests/relu.py
tests/resnet18.py
tests/resnet18_channels_last.py
tests/resnet34.py
tests/resnet50.py
tests/senet.py
tests/sigmoid.py
tests/softmax.py
tests/squeezenet.py
tests/sub.py
tests/sum.py
tests/tanh.py
tests/transpose.py
tests/upsample_nearest.py
tests/vgg11.py
tests/view.py
tests/layers/__init__.py
tests/layers/avg_pool.py
tests/layers/bn.py
tests/layers/channel_shuffle.py
tests/layers/concat_many.py
tests/layers/const.py
tests/layers/conv2d.py
tests/layers/conv2d_channels_last.py
tests/layers/conv2d_dilation.py
tests/layers/conv3d.py
tests/layers/convtranspose2d.py
tests/layers/dense.py
tests/layers/densenet.py
tests/layers/depthwise_conv2d.py
tests/layers/droupout.py
tests/layers/embedding.py
tests/layers/group_conv2d.py
tests/layers/instance_norm.py
tests/layers/lrelu.py
tests/layers/max_pool.py
tests/layers/max_pool3d.py
tests/layers/module_list.py
tests/layers/mul.py
tests/layers/multiple_inputs.py
tests/layers/relu.py
tests/layers/sigmoid.py
tests/layers/slice.py
tests/layers/softmax.py
tests/layers/sub.py
tests/layers/sum.py
tests/layers/tanh.py
tests/layers/transpose.py
tests/layers/upsample_nearest.py
tests/layers/view.py
tests/models/__init__.py
tests/models/alexnet.py
tests/models/darknet.py
tests/models/enet.py
tests/models/menet.py
tests/models/mobilinet.py
tests/models/preresnet18.py
tests/models/resnet18.py
tests/models/resnet18_channels_last.py
tests/models/resnet34.py
tests/models/resnet50.py
tests/models/senet.py
