Metadata-Version: 2.1
Name: pytorch2keras
Version: 0.1.5
Summary: The deep learning models convertor
Home-page: https://github.com/nerox8664/pytorch2keras
Author: Grigory Malivenko
Author-email: nerox8664@gmail.com
License: MIT
Platform: UNKNOWN
Requires-Dist: keras (==2.2.2)
Requires-Dist: tensorflow (==1.9.0)
Requires-Dist: numpy (==1.14.1)
Requires-Dist: torch (==0.4)
Requires-Dist: torchvision (==0.2.1)
